iam_sarif_report/__init__.py
iam_sarif_report/bootstrap.py
iam_sarif_report/checks.json
iam_sarif_report/adapters/__init__.py
iam_sarif_report/adapters/checks.py
iam_sarif_report/adapters/reader.py
iam_sarif_report/adapters/reporter.py
iam_sarif_report/adapters/validator.py
iam_sarif_report/domain/__init__.py
iam_sarif_report/domain/commands.py
iam_sarif_report/domain/converter.py
iam_sarif_report/domain/definitions.py
iam_sarif_report/entrypoints/__init__.py
iam_sarif_report/entrypoints/cli.py
iam_sarif_report/service_layer/__init__.py
iam_sarif_report/service_layer/bus.py
iam_sarif_report/service_layer/handlers.py
iam_sarif_report-2.3.4.dist-info/licenses/LICENSE
iam_sarif_report-2.3.4.dist-info/METADATA
iam_sarif_report-2.3.4.dist-info/WHEEL
iam_sarif_report-2.3.4.dist-info/entry_points.txt
iam_sarif_report-2.3.4.dist-info/top_level.txt
iam_sarif_report-2.3.4.dist-info/RECORD
