Metadata-Version: 2.4
Name: iam-sarif-report
Version: 2.3.4
Author-email: George Alton <georgealton@gmail.com>
License: MIT License
Project-URL: homepage, https://github.com/georgealton/iam-sarif-report
Project-URL: repository, https://github.com/georgealton/iam-sarif-report
Classifier: Intended Audience :: Developers
Classifier: License :: OSI Approved :: MIT License
Classifier: Operating System :: OS Independent
Classifier: Programming Language :: Python
Classifier: Programming Language :: Python :: 3.8
Classifier: Programming Language :: Python :: 3.9
Classifier: Programming Language :: Python :: 3.10
Classifier: Programming Language :: Python :: 3.11
Classifier: Programming Language :: Python :: 3.12
Classifier: Topic :: Software Development :: Libraries :: Python Modules
Requires-Python: >=3.8
License-File: LICENSE
Requires-Dist: attrs==25.3.0
Requires-Dist: click==8.1.8
Requires-Dist: punq==0.7.0
Requires-Dist: boto3==1.39.14
Requires-Dist: sarif_om==1.0.4
Requires-Dist: jschema_to_python==1.2.3
Provides-Extra: dev
Requires-Dist: black; extra == "dev"
Requires-Dist: mypy; extra == "dev"
Requires-Dist: nox; extra == "dev"
Requires-Dist: ruff; extra == "dev"
Requires-Dist: pre-commit; extra == "dev"
Requires-Dist: iam-sarif-report[docs,test,types]; extra == "dev"
Provides-Extra: types
Requires-Dist: mypy_boto3_accessanalyzer; extra == "types"
Requires-Dist: types-setuptools; extra == "types"
Provides-Extra: docs
Requires-Dist: mkdocs; extra == "docs"
Requires-Dist: mkdocs-material; extra == "docs"
Requires-Dist: mkdocstrings; extra == "docs"
Provides-Extra: test
Requires-Dist: pytest; extra == "test"
Requires-Dist: pytest-sugar; extra == "test"
Requires-Dist: pytest-cov; extra == "test"
Requires-Dist: pytest-datadir; extra == "test"
Requires-Dist: jsonschema; extra == "test"
Provides-Extra: scraper
Requires-Dist: beautifulsoup4; extra == "scraper"
Requires-Dist: requests; extra == "scraper"
Requires-Dist: html2text; extra == "scraper"
Dynamic: license-file
